<?xml version="1.0" encoding="UTF-8" standalone="yes"?>
<ns2:manifest xmlns:ns2="http://nxp.com/ksdk/2.0/ksdk_manifest_v3.0.xsd" format_version="3.9" api_version="2.0.0" configuration="a22c1eabe6441f1d1e0aabdd0041c82f" id="SDK_2.x_MK22FN512xxx12" name="MK22FN512xxx12" brief="This is SDK version 2.11.0 manifest file. It describes the content of the MK22FN512xxx12 and additional settings for tools that support SDK version 2.11.0">
    <defines>
        <define name="CPU_$|package|" value=""/>
        <define name="CPU_$|package|_$|core|" value=""/>
    </defines>
    <externalDefinitions>
        <definition extID="twrk22f120m"/>
    </externalDefinitions>
    <ksdk id="MCUXpresso2110" name="MCUXpresso2110" version="2.11.0" revision="541 2022-01-14"/>
    <compilers>
        <compiler type="gcc" id="compiler_gcc" name="gcc"/>
    </compilers>
    <toolchainSettings>
        <toolchainSetting id="com.nxp.mcuxpresso" name="mcuxpresso" full_name="MCUXpresso IDE" version="11.5.0" toolchain="mcuxpresso" compiler="compiler_gcc">
            <option id="gnu.cpp.compiler.option.optimization.flags" type="string" user_name="">
                <value>-fno-common</value>
            </option>
            <option id="gnu.c.compiler.option.optimization.flags" type="string" user_name="">
                <value>-fno-common</value>
            </option>
            <option id="gnu.cpp.link.option.nostdlibs" type="boolean" user_name="">
                <value>true</value>
            </option>
            <option id="com.crt.advproject.link.cpp.flashconfigenable" type="boolean" user_name="">
                <value>true</value>
            </option>
            <option id="com.crt.advproject.link.flashconfigenable" type="boolean" user_name="">
                <value>true</value>
            </option>
            <option id="gnu.c.link.option.nostdlibs" type="boolean" user_name="">
                <value>true</value>
            </option>
        </toolchainSetting>
    </toolchainSettings>
    <toolchains>
        <toolchain type="mcuxpresso" vendor="NXP Semiconductors" vendor_url="http://www.nxp.com" id="mcuxpresso" name="MCUXpresso_IDE" full_name="MCUXpresso IDE" version="11.5.0" compiler="compiler_gcc">
            <debug>
                <debug_configuration probe="LinkServer" id="com.crt.advproject.config.exe.release" name="Release Configuration">
                    <scripts>
                        <script type="init" silent="false" emulators="${gdb.stub} -mi -info-emu">
                            <script>
set remotetimeout 60000
##target_extended_remote##
set mem inaccessible-by-default ${mem.access}
mon ondisconnect ${ondisconnect}
set arm force-mode thumb
${load}</script>
                        </script>
                        <script type="run" silent="false" emulators="${gdb.stub} -mi -info-emu">
                            <script>${run}</script>
                        </script>
                    </scripts>
                    <params>
                        <params value="false" id="vector.catch.release.mcuxpresso" name="vector.catch"/>
                        <params value="Disable" id="internal.cache.release.mcuxpresso" name="internal.cache"/>
                    </params>
                </debug_configuration>
                <debug_configuration probe="LinkServer" id="com.crt.advproject.config.exe.debug" name="Debug Configuration">
                    <scripts>
                        <script type="init" silent="false" emulators="${gdb.stub} -mi -info-emu">
                            <script>
set remotetimeout 60000
##target_extended_remote##
set mem inaccessible-by-default ${mem.access}
mon ondisconnect ${ondisconnect}
set arm force-mode thumb
${load}</script>
                        </script>
                        <script type="run" silent="false" emulators="${gdb.stub} -mi -info-emu">
                            <script>${run}</script>
                        </script>
                    </scripts>
                    <params>
                        <params value="false" id="vector.catch.debug.mcuxpresso" name="vector.catch"/>
                        <params value="Disable" id="internal.cache.debug.mcuxpresso" name="internal.cache"/>
                    </params>
                </debug_configuration>
                <debug_configuration probe="Segger" id="com.nxp.mcuxpresso.core.debug.support.segger.debug" name="Debug Configuration"/>
                <debug_configuration probe="Segger" id="com.nxp.mcuxpresso.core.debug.support.segger.release" name="Release Configuration"/>
            </debug>
        </toolchain>
    </toolchains>
    <boards>
        <board package="MK22FN512VLH12" id="frdmk22f" name="FRDM-K22F" href="https://www.nxp.com/pip/FRDM-K22F" version="1.0.0">
            <description>Freedom Development Board for Kinetis K02 and K22 (100-120 MHz, 128-512 KB Flash) MCUs</description>
            <image path="boards/frdmk22f" type="image">
                <files mask="frdmk22f.png"/>
            </image>
            <total_memory flash_size_kb="0" ram_size_kb="0"/>
        </board>
        <board package="MK22FN512VLH12" type="kit" id="frdmk22f_agm01" name="FRDM-K22F-AGM01" href="https://www.nxp.com/pip/FRDM-STBC-AGM01" version="1.0.0">
            <description>Freedom Development Platform for Kinetis K22 MCU with 9-Axis sensor shield board FRDM-STBC-AGM01 having FXAS21002C Gyroscope &amp; FXOS8700CQ E-compass sensors.</description>
            <image path="boards/frdmk22f_agm01" type="image">
                <files mask="frdmk22f_agm01.png"/>
            </image>
            <total_memory flash_size_kb="0" ram_size_kb="0"/>
        </board>
        <board package="MK22FN512VLH12" type="kit" id="frdmk22f_agmp03" name="FRDM-K22F-AGMP03" href="https://www.nxp.com/pip/FRDM-K22F-AGMP03" version="1.0.0">
            <description>Freedom Development Board for Kinetis K02 and K22 MCUs with Sensor Development Shield Board for MPXx5004 Differential and Gauge, Integrated Analog Pressure Sensor </description>
            <image path="boards/frdmk22f_agmp03" type="image">
                <files mask="frdmk22f_agmp03.png"/>
            </image>
            <total_memory flash_size_kb="0" ram_size_kb="0"/>
        </board>
        <board package="MK22FN512VLH12" type="kit" id="frdmk22f_sa9500" name="FRDM-K22F-SA9500" href="https://www.nxp.com/pip/FRDM-STBC-SA9500" version="1.0.0">
            <description>Freedom Development Board for Kinetis K22 MCUs with sensor shield board FRDM-STBC-SA9500 having FXLC95000CL Intelligent Motion Sensor</description>
            <image path="boards/frdmk22f_sa9500" type="image">
                <files mask="frdmk22f_sa9500.png"/>
            </image>
            <total_memory flash_size_kb="0" ram_size_kb="0"/>
        </board>
        <board package="MK22FN512VLH12" type="kit" id="frdmk22f_a8964" name="FRDM-K22F-A8964" href="https://www.nxp.com/pip/FRDM-K22F" version="1.0.0">
            <description>FRDM-K22F evaluation kit with FRDM-STBA-A8964 sensor shield board having FXLS8964AF ultra-low- power motion wakeup sensor</description>
            <image path="boards/frdmk22f_a8964" type="image">
                <files mask="frdmk22f_a8964.png"/>
            </image>
            <total_memory flash_size_kb="0" ram_size_kb="0"/>
        </board>
    </boards>
    <devices>
        <device family="K2x" platform="Kinetis" id="MK22FN512xxx12" name="MK22F51212" full_name="MK22FN512xxx12" version="1.0.0">
            <description>Kinetis K22-120 MHz, Cost Effective, Full-Speed USB Microcontrollers (MCUs) based on ARM Cortex-M4 Core</description>
            <metadataSet>
                <metadata key="USB_KHCI_COUNT" value="1"/>
                <metadata key="vendor" value="NXP"/>
            </metadataSet>
            <core fpu="true" type="cm4" id="core0_MK22FN512xxx12" name="core0"/>
            <memory>
                <memoryBlock addr="00000000" size="00080000" type="Flash" access="RO" id="PROGRAM_FLASH_MK22FN512xxx12" name="PROGRAM_FLASH"/>
                <memoryBlock addr="20000000" size="00010000" type="RAM" access="RW" id="SRAM_UPPER_MK22FN512xxx12" name="SRAM_UPPER"/>
                <memoryBlock addr="1FFF0000" size="00010000" type="RAM" access="RW" id="SRAM_LOWER_MK22FN512xxx12" name="SRAM_LOWER"/>
            </memory>
            <total_memory flash_size_kb="512" ram_size_kb="64"/>
            <package id="MK22FN512VDC12" name="MK22FN512VDC12"/>
            <package id="MK22FN512VLL12" name="MK22FN512VLL12"/>
            <package id="MK22FN512VLH12" name="MK22FN512VLH12"/>
            <package id="MK22FN512VFX12" name="MK22FN512VFX12"/>
            <package id="MK22FN512CAP12" name="MK22FN512CAP12"/>
            <package id="MK22FN512VMP12" name="MK22FN512VMP12"/>
            <evaluation_boards>
                <evaluation_board name="frdmk22f"/>
            </evaluation_boards>
            <debug_configurations>
                <debug_configuration id_refs="com.crt.advproject.config.exe.debug com.crt.advproject.config.exe.release">
                    <params>
                        <params value="SWD*,JTAG" id="internal.wiretype.release.MK22FN512xxx12" name="internal.wiretype"/>
                        <params value="true" id="internal.has_swo.release.MK22FN512xxx12" name="internal.has_swo"/>
                        <params value="kinetisconnect.scp" id="internal.connect.script.debug.mcuxpresso.MK22FN512xxx12" name="internal.connect.script"/>
                    </params>
                    <drivers>
                        <driver id_refs="PROGRAM_FLASH_MK22FN512xxx12">
                            <driverBinary path="devices/MK22F51212/mcuxpresso" type="binary">
<files mask="FTFA_2K.cfx"/>
                            </driverBinary>
                        </driver>
                    </drivers>
                </debug_configuration>
            </debug_configurations>
            <linkerSettings nature="c_nature">
                <linker property="start_symbol" value="ResetISR"/>
                <linker property="text_align" value="4"/>
                <linker property="data_align" value="4"/>
                <linker property="bss_align" value="4"/>
                <linker property="flash_security_address" value="0x400"/>
                <linker property="mtb_supported" value="false"/>
            </linkerSettings>
            <linkerSettings nature="cpp_nature">
                <linker property="start_symbol" value="ResetISR"/>
                <linker property="text_align" value="4"/>
                <linker property="data_align" value="4"/>
                <linker property="bss_align" value="4"/>
                <linker property="flash_security_address" value="0x400"/>
                <linker property="mtb_supported" value="false"/>
            </linkerSettings>
        </device>
    </devices>
    <components>
        <component user_visible="true" type="debugger" devices="MK22FN512xxx12" device_cores="" package_base_path="devices/MK22F51212" project_base_path="MK22F51212" id="device.MK22F51212_debugger.MK22F51212" name="MK22F51212_debugger" full_name="Device MK22F51212_debugger" brief="Device MK22F51212_debugger" version="1.0.0">
            <source relative_path="./" type="xml">
                <files mask="MK22F51212.xml"/>
            </source>
        </component>
    </components>
</ns2:manifest>
